[
    {
        "TableNames": "customer",
        "_id": "browsecustomer",
        "IsAdd": true,
        "IsEdit": true,
        "MetaData": [
            {
                "AdvanceFilter": false,
                "Aggregate": "",
                "Align": "Left",
                "DataType": "string",
                "Field": "_id",
                "Format": "",
                "HiddenField": false,
                "Label": "Outlet ID",
                "Lookup": true,
                "ShowIndex": 1,
                "SimpleFilter": true,
                "Sortable": true,
                "IsAdd": true,
                "IsEdit": true
            },
            {
                "AdvanceFilter": false,
                "Aggregate": "",
                "Align": "Left",
                "DataType": "string",
                "Field": "customerid",
                "Format": "",
                "HiddenField": false,
                "Label": "Customer ID",
                "Lookup": true,
                "ShowIndex": 2,
                "SimpleFilter": true,
                "Sortable": true,
                "IsAdd": true,
                "IsEdit": true
            },
            {
                "AdvanceFilter": false,
                "Aggregate": "",
                "Align": "Left",
                "DataType": "string",
                "Field": "plant",
                "Format": "",
                "HiddenField": false,
                "Label": "Plant",
                "Lookup": true,
                "ShowIndex": 3,
                "SimpleFilter": true,
                "Sortable": true,
                "IsAdd": true,
                "IsEdit": true
            },
            {
                "AdvanceFilter": false,
                "Aggregate": "",
                "Align": "Left",
                "DataType": "string",
                "Field": "name",
                "Format": "",
                "HiddenField": false,
                "Label": "Name",
                "Lookup": true,
                "ShowIndex": 4,
                "SimpleFilter": true,
                "Sortable": true,
                "IsAdd": true,
                "IsEdit": true
            },
            {
                "AdvanceFilter": false,
                "Aggregate": "",
                "Align": "Left",
                "DataType": "string",
                "Field": "keyaccount",
                "Format": "",
                "HiddenField": false,
                "Label": "Key Account",
                "Lookup": true,
                "ShowIndex": 5,
                "SimpleFilter": true,
                "Sortable": true,
                "IsAdd": true,
                "IsEdit": true
            },
            {
                "AdvanceFilter": false,
                "Aggregate": "",
                "Align": "Left",
                "DataType": "int",
                "Field": "channel",
                "Format": "",
                "HiddenField": false,
                "Label": "Channel",
                "Lookup": true,
                "ShowIndex": 6,
                "SimpleFilter": true,
                "Sortable": true,
                "IsAdd": true,
                "IsEdit": true
            },
            {
                "AdvanceFilter": false,
                "Aggregate": "",
                "Align": "Left",
                "DataType": "string",
                "Field": "group",
                "Format": "",
                "HiddenField": false,
                "Label": "Group",
                "Lookup": true,
                "ShowIndex": 7,
                "SimpleFilter": true,
                "Sortable": true,
                "IsAdd": true,
                "IsEdit": true
            },
            {
                "AdvanceFilter": false,
                "Aggregate": "",
                "Align": "Left",
                "DataType": "string",
                "Field": "national",
                "Format": "",
                "HiddenField": false,
                "Label": "National",
                "Lookup": true,
                "ShowIndex": 8,
                "SimpleFilter": true,
                "Sortable": true,
                "IsAdd": true,
                "IsEdit": true
            },
            {
                "AdvanceFilter": false,
                "Aggregate": "",
                "Align": "Left",
                "DataType": "string",
                "Field": "zone",
                "Format": "",
                "HiddenField": false,
                "Label": "Zone",
                "Lookup": true,
                "ShowIndex": 9,
                "SimpleFilter": true,
                "Sortable": true,
                "IsAdd": true,
                "IsEdit": true
            },
            {
                "AdvanceFilter": false,
                "Aggregate": "",
                "Align": "Left",
                "DataType": "string",
                "Field": "region",
                "Format": "",
                "HiddenField": false,
                "Label": "Region",
                "Lookup": true,
                "ShowIndex": 10,
                "SimpleFilter": true,
                "Sortable": true,
                "IsAdd": true,
                "IsEdit": true
            },
            {
                "AdvanceFilter": false,
                "Aggregate": "",
                "Align": "Left",
                "DataType": "string",
                "Field": "area",
                "Format": "",
                "HiddenField": false,
                "Label": "Area",
                "Lookup": true,
                "ShowIndex": 11,
                "SimpleFilter": true,
                "Sortable": true,
                "IsAdd": true,
                "IsEdit": true
            }
        ]
    },
    {
        "TableNames": "branch",
        "_id": "browsebranch",
        "IsAdd": true,
        "IsEdit": true,
        "MetaData": [
            {
                "AdvanceFilter": false,
                "Aggregate": "",
                "Align": "Left",
                "DataType": "string",
                "Field": "_id",
                "Format": "",
                "HiddenField": false,
                "Label": "Branch ID",
                "Lookup": true,
                "ShowIndex": 1,
                "SimpleFilter": true,
                "Sortable": true,
                "IsAdd": true,
                "IsEdit": true
            },
            {
                "AdvanceFilter": false,
                "Aggregate": "",
                "Align": "Left",
                "DataType": "string",
                "Field": "name",
                "Format": "",
                "HiddenField": false,
                "Label": "Name",
                "Lookup": true,
                "ShowIndex": 2,
                "SimpleFilter": true,
                "Sortable": true,
                "IsAdd": true,
                "IsEdit": true
            },
            {
                "AdvanceFilter": false,
                "Aggregate": "",
                "Align": "Left",
                "DataType": "string",
                "Field": "location",
                "Format": "",
                "HiddenField": false,
                "Label": "Location",
                "Lookup": true,
                "ShowIndex": 3,
                "SimpleFilter": true,
                "Sortable": true,
                "IsAdd": true,
                "IsEdit": true
            }
        ]
    },
    {
        "TableNames": "product",
        "_id": "browseproduct",
        "IsAdd": true,
        "IsEdit": true,
        "MetaData": [
            {
                "AdvanceFilter": false,
                "Aggregate": "",
                "Align": "Left",
                "DataType": "string",
                "Field": "_id",
                "Format": "",
                "HiddenField": false,
                "Label": "SKUID",
                "Lookup": true,
                "ShowIndex": 1,
                "SimpleFilter": true,
                "Sortable": true,
                "IsAdd": true,
                "IsEdit": true
            },
            {
                "AdvanceFilter": false,
                "Aggregate": "",
                "Align": "Left",
                "DataType": "string",
                "Field": "name",
                "Format": "",
                "HiddenField": false,
                "Label": "Name",
                "Lookup": true,
                "ShowIndex": 2,
                "SimpleFilter": true,
                "Sortable": true,
                "IsAdd": true,
                "IsEdit": true
            },
            {
                "AdvanceFilter": false,
                "Aggregate": "",
                "Align": "Left",
                "DataType": "string",
                "Field": "config",
                "Format": "",
                "HiddenField": false,
                "Label": "Config",
                "Lookup": true,
                "ShowIndex": 3,
                "SimpleFilter": true,
                "Sortable": true,
                "IsAdd": true,
                "IsEdit": true
            },
            {
                "AdvanceFilter": false,
                "Aggregate": "",
                "Align": "Left",
                "DataType": "string",
                "Field": "brand",
                "Format": "",
                "HiddenField": false,
                "Label": "Brand",
                "Lookup": true,
                "ShowIndex": 4,
                "SimpleFilter": true,
                "Sortable": true,
                "IsAdd": true,
                "IsEdit": true
            },
            {
                "AdvanceFilter": false,
                "Aggregate": "",
                "Align": "Left",
                "DataType": "string",
                "Field": "longname",
                "Format": "",
                "HiddenField": false,
                "Label": "Long Name",
                "Lookup": true,
                "ShowIndex": 5,
                "SimpleFilter": true,
                "Sortable": true,
                "IsAdd": true,
                "IsEdit": true
            }
        ]
    },
    {
        "TableNames": "costcenter",
        "_id": "browsecostcenterr",
        "IsAdd": true,
        "IsEdit": true,
        "MetaData": [
            {
                "AdvanceFilter": false,
                "Aggregate": "",
                "Align": "Left",
                "DataType": "string",
                "Field": "_id",
                "Format": "",
                "HiddenField": false,
                "Label": "ID",
                "Lookup": true,
                "ShowIndex": 1,
                "SimpleFilter": true,
                "Sortable": true,
                "IsAdd": true,
                "IsEdit": true
            },
            {
                "AdvanceFilter": false,
                "Aggregate": "",
                "Align": "Left",
                "DataType": "string",
                "Field": "entityid",
                "Format": "",
                "HiddenField": false,
                "Label": "Entity ID",
                "Lookup": true,
                "ShowIndex": 2,
                "SimpleFilter": true,
                "Sortable": true,
                "IsAdd": true,
                "IsEdit": true
            },
            {
                "AdvanceFilter": false,
                "Aggregate": "",
                "Align": "Left",
                "DataType": "string",
                "Field": "name",
                "Format": "",
                "HiddenField": false,
                "Label": "Name",
                "Lookup": true,
                "ShowIndex": 3,
                "SimpleFilter": true,
                "Sortable": true,
                "IsAdd": true,
                "IsEdit": true
            },
            {
                "AdvanceFilter": false,
                "Aggregate": "",
                "Align": "Left",
                "DataType": "string",
                "Field": "costgroup01",
                "Format": "",
                "HiddenField": false,
                "Label": "Cost Group 01",
                "Lookup": true,
                "ShowIndex": 4,
                "SimpleFilter": true,
                "Sortable": true,
                "IsAdd": true,
                "IsEdit": true
            },
            {
                "AdvanceFilter": false,
                "Aggregate": "",
                "Align": "Left",
                "DataType": "string",
                "Field": "costgroup02",
                "Format": "",
                "HiddenField": false,
                "Label": "Cost Group 02",
                "Lookup": true,
                "ShowIndex": 5,
                "SimpleFilter": true,
                "Sortable": true,
                "IsAdd": true,
                "IsEdit": true
            },
            {
                "AdvanceFilter": false,
                "Aggregate": "",
                "Align": "Left",
                "DataType": "string",
                "Field": "costgroup03",
                "Format": "",
                "HiddenField": false,
                "Label": "Cost Group 03",
                "Lookup": true,
                "ShowIndex": 6,
                "SimpleFilter": true,
                "Sortable": true,
                "IsAdd": true,
                "IsEdit": true
            },
            {
                "AdvanceFilter": false,
                "Aggregate": "",
                "Align": "Left",
                "DataType": "string",
                "Field": "branchid",
                "Format": "",
                "HiddenField": false,
                "Label": "Branch ID",
                "Lookup": true,
                "ShowIndex": 7,
                "SimpleFilter": true,
                "Sortable": true,
                "IsAdd": true,
                "IsEdit": true
            },
            {
                "AdvanceFilter": false,
                "Aggregate": "",
                "Align": "Left",
                "DataType": "int",
                "Field": "branchtype",
                "Format": "",
                "HiddenField": false,
                "Label": "Branch Type",
                "Lookup": true,
                "ShowIndex": 8,
                "SimpleFilter": true,
                "Sortable": true,
                "IsAdd": true,
                "IsEdit": true
            }
        ]
    },
    {
        "TableNames": "profitcenter",
        "_id": "browseprofitcenter",
        "IsAdd": true,
        "IsEdit": true,
        "MetaData": [
            {
                "AdvanceFilter": false,
                "Aggregate": "",
                "Align": "Left",
                "DataType": "string",
                "Field": "_id",
                "Format": "",
                "HiddenField": false,
                "Label": "ID",
                "Lookup": true,
                "ShowIndex": 1,
                "SimpleFilter": true,
                "Sortable": true,
                "IsAdd": true,
                "IsEdit": true
            },
            {
                "AdvanceFilter": false,
                "Aggregate": "",
                "Align": "Left",
                "DataType": "string",
                "Field": "entityid",
                "Format": "",
                "HiddenField": false,
                "Label": "Entity ID",
                "Lookup": true,
                "ShowIndex": 2,
                "SimpleFilter": true,
                "Sortable": true,
                "IsAdd": true,
                "IsEdit": true
            },
            {
                "AdvanceFilter": false,
                "Aggregate": "",
                "Align": "Left",
                "DataType": "string",
                "Field": "name",
                "Format": "",
                "HiddenField": false,
                "Label": "Name",
                "Lookup": true,
                "ShowIndex": 3,
                "SimpleFilter": true,
                "Sortable": true,
                "IsAdd": true,
                "IsEdit": true
            },
            {
                "AdvanceFilter": false,
                "Aggregate": "",
                "Align": "Left",
                "DataType": "string",
                "Field": "brand",
                "Format": "",
                "HiddenField": false,
                "Label": "Brand",
                "Lookup": true,
                "ShowIndex": 4,
                "SimpleFilter": true,
                "Sortable": true,
                "IsAdd": true,
                "IsEdit": true
            },
            {
                "AdvanceFilter": false,
                "Aggregate": "",
                "Align": "Left",
                "DataType": "string",
                "Field": "branchid",
                "Format": "",
                "HiddenField": false,
                "Label": "Branch ID",
                "Lookup": true,
                "ShowIndex": 5,
                "SimpleFilter": true,
                "Sortable": true,
                "IsAdd": true,
                "IsEdit": true
            },
            {
                "AdvanceFilter": false,
                "Aggregate": "",
                "Align": "Left",
                "DataType": "int",
                "Field": "branchtype",
                "Format": "",
                "HiddenField": false,
                "Label": "Branch Type",
                "Lookup": true,
                "ShowIndex": 6,
                "SimpleFilter": true,
                "Sortable": true,
                "IsAdd": true,
                "IsEdit": true
            }
        ]
    },
    {
        "TableNames": "truck",
        "_id": "browsetruck",
        "IsAdd": true,
        "IsEdit": true,
        "MetaData": [
            {
                "AdvanceFilter": false,
                "Aggregate": "",
                "Align": "Left",
                "DataType": "string",
                "Field": "_id",
                "Format": "",
                "HiddenField": false,
                "Label": "ID",
                "Lookup": true,
                "ShowIndex": 1,
                "SimpleFilter": true,
                "Sortable": true,
                "IsAdd": true,
                "IsEdit": true
            },
            {
                "AdvanceFilter": false,
                "Aggregate": "",
                "Align": "Left",
                "DataType": "string",
                "Field": "branchid",
                "Format": "",
                "HiddenField": false,
                "Label": "Branch ID",
                "Lookup": true,
                "ShowIndex": 2,
                "SimpleFilter": true,
                "Sortable": true,
                "IsAdd": true,
                "IsEdit": true
            },
            {
                "AdvanceFilter": false,
                "Aggregate": "",
                "Align": "Left",
                "DataType": "string",
                "Field": "plateno",
                "Format": "",
                "HiddenField": false,
                "Label": "Plate No",
                "Lookup": true,
                "ShowIndex": 3,
                "SimpleFilter": true,
                "Sortable": true,
                "IsAdd": true,
                "IsEdit": true
            },
            {
                "AdvanceFilter": false,
                "Aggregate": "",
                "Align": "Left",
                "DataType": "int",
                "Field": "year",
                "Format": "",
                "HiddenField": false,
                "Label": "Year",
                "Lookup": true,
                "ShowIndex": 4,
                "SimpleFilter": true,
                "Sortable": true,
                "IsAdd": true,
                "IsEdit": true
            }
        ]
    }
]